bin/__init__.py
bin/codebase-indexer.py
bin/codebase_indexer.py
codebase_indexer-1.2.2.data/scripts/codebase-indexer.py
codebase_indexer-1.2.2.dist-info/licenses/LICENSE
src/__init__.py
src/main.py
src/test_cli.py
src/verify_setup.py
src/agents/__init__.py
src/agents/code_agent.py
src/indexers/__init__.py
src/indexers/code_indexer.py
src/models/__init__.py
src/models/embeddings.py
src/models/llm.py
src/utils/__init__.py
src/utils/code_analysis.py
src/utils/code_splitter.py
src/utils/commands.py
src/utils/config.py
src/utils/file_utils.py
src/utils/logger.py
src/utils/pinecone_utils.py
src/utils/project_metadata.py
codebase_indexer-1.2.2.dist-info/METADATA
codebase_indexer-1.2.2.dist-info/WHEEL
codebase_indexer-1.2.2.dist-info/entry_points.txt
codebase_indexer-1.2.2.dist-info/top_level.txt
codebase_indexer-1.2.2.dist-info/RECORD
