Metadata-Version: 2.4
Name: codebase-indexer
Version: 1.2.2
Summary: A command-line tool for indexing and querying large codebases using AI
Home-page: https://github.com/RajwardhanShinde/Code-Indexer
Author: Rajwardhan Shinde
Author-email: rajshinde55553@example.com
Keywords: code,indexing,search,AI,embeddings,RAG,retrieval,Claude,OpenAI,Pinecone
Classifier: Development Status :: 5 - Production/Stable
Classifier: Intended Audience :: Developers
Classifier: Topic :: Software Development :: Libraries :: Python Modules
Classifier: License :: OSI Approved :: MIT License
Classifier: Programming Language :: Python :: 3
Classifier: Programming Language :: Python :: 3.8
Classifier: Programming Language :: Python :: 3.9
Classifier: Programming Language :: Python :: 3.10
Classifier: Programming Language :: Python :: 3.11
Requires-Python: >=3.8
License-File: LICENSE
Requires-Dist: langchain
Requires-Dist: langchain-community
Requires-Dist: langchain-openai
Requires-Dist: langchain-anthropic
Requires-Dist: langchain-pinecone
Requires-Dist: openai
Requires-Dist: pinecone
Requires-Dist: anthropic
Requires-Dist: python-dotenv
Requires-Dist: tiktoken
Requires-Dist: tqdm
Dynamic: author
Dynamic: author-email
Dynamic: classifier
Dynamic: description
Dynamic: description-content-type
Dynamic: home-page
Dynamic: keywords
Dynamic: license-file
Dynamic: requires-dist
Dynamic: requires-python
Dynamic: summary
